epicdb/__init__.py
epicdb/epicdb.py
epicdb/db/__init__.py
epicdb/db/epicdb.feather
epicdb-1.6.dist-info/METADATA
epicdb-1.6.dist-info/WHEEL
epicdb-1.6.dist-info/top_level.txt
epicdb-1.6.dist-info/RECORD
