Metadata-Version: 2.1
Name: epicdb
Version: 1.6
Summary: A python package to use the Environmental Performance in Construction (EPiC) Database as a Pandas Dataframe
Home-page: https://github.com/hybridlca/epicdb
Author: André Stephan
Author-email: stephan.andre@gmail.com
License: GNU General Public License v3.0
Requires-Dist: pandas
Requires-Dist: pyarrow
